{
    "builds": [
      {
        "path": "soljson-v0.8.28-js-revive-0.1.0-dev.7.js",
        "version": "0.8.28-js",
        "build": "revive-0.1.0-dev.7",
        "longVersion": "0.8.28-js-revive-0.1.0-dev.7",
        "urls": [
        ]
      },
      {
        "path": "soljson-v0.8.28-backend-revive-0.1.0-dev.7.js",
        "version": "0.8.28-backend",
        "build": "revive-0.1.0-dev.7",
        "longVersion": "0.8.28-backend-revive-0.1.0-dev.7",
        "urls": [
        ]
      }
    ],
    "releases": {
       "0.8.28-js": "soljson-v0.8.28-js-revive-0.1.0-dev.7.js",
       "0.8.28-backend": "soljson-v0.8.28-backend-revive-0.1.0-dev.7"
    },
    "latestRelease": "0.8.28-js"
  }